py2swagger/schema_builder.py
py2swagger/introspector.py
py2swagger/utils.py
py2swagger/yamlparser.py
py2swagger/config.py
py2swagger/__init__.py
py2swagger/plugins/simple.py
py2swagger/plugins/falcon.py
py2swagger/plugins/falcon.py2swagger
py2swagger/plugins/drf.py2swagger
py2swagger/plugins/simple.py2swagger
py2swagger/plugins/__init__.py
py2swagger/plugins/drf/injection.py
py2swagger/plugins/drf/exceptions.py
py2swagger/plugins/drf/urlparser.py
py2swagger/plugins/drf/__init__.py
py2swagger/plugins/drf/introspectors/api.py
py2swagger/plugins/drf/introspectors/serializer.py
py2swagger/plugins/drf/introspectors/authentication.py
py2swagger/plugins/drf/introspectors/method.py
py2swagger/plugins/drf/introspectors/view.py
py2swagger/plugins/drf/introspectors/pagination.py
py2swagger/plugins/drf/introspectors/filter.py
py2swagger/plugins/drf/introspectors/__init__.py
py2swagger-1.0.0.dist-info/entry_points.txt
py2swagger-1.0.0.dist-info/RECORD
py2swagger-1.0.0.dist-info/DESCRIPTION.rst
py2swagger-1.0.0.dist-info/top_level.txt
py2swagger-1.0.0.dist-info/METADATA
py2swagger-1.0.0.dist-info/WHEEL
py2swagger-1.0.0.dist-info/metadata.json
