Metadata-Version: 2.0
Name: py2swagger
Version: 1.0.0
Summary: Swagger schema builder
Home-page: https://github.com/Arello-Mobile/py2swagger
Author: Arello Mobile
Author-email: UNKNOWN
License: MIT
Platform: Posix; MacOS X; Windows
Classifier: Development Status :: 4 - Beta
Classifier: Intended Audience :: Developers
Classifier: License :: OSI Approved :: MIT License
Classifier: Operating System :: OS Independent
Classifier: Programming Language :: Python :: 2
Classifier: Programming Language :: Python :: 2.7
Classifier: Programming Language :: Python :: 3
Classifier: Programming Language :: Python :: 3.3
Classifier: Programming Language :: Python :: 3.4
Classifier: Programming Language :: Python :: 3.5
Classifier: Topic :: Software Development :: Documentation
Requires-Dist: PyYAML (>=3.10)
Requires-Dist: six
Requires-Dist: yapsy (>=1.11.223)
Provides-Extra: reST
Requires-Dist: docutils (>=0.8); extra == 'reST'
Provides-Extra: testing
Requires-Dist: nose; extra == 'testing'
Requires-Dist: rednose; extra == 'testing'
Requires-Dist: mock; extra == 'testing'
Requires-Dist: coverage; extra == 'testing'
Requires-Dist: Django (<=1.10); extra == 'testing'
Requires-Dist: djangorestframework; extra == 'testing'
Requires-Dist: falcon; extra == 'testing'
Requires-Dist: bottle; extra == 'testing'
Requires-Dist: flask; extra == 'testing'
